tket2_exts/__init__.py
tket2_exts/py.typed
tket2_exts-0.10.0.dist-info/METADATA
tket2_exts-0.10.0.dist-info/WHEEL
tket2_exts-0.10.0.dist-info/licenses/LICENCE
tket2_exts-0.10.0.dist-info/RECORD
