Metadata-Version: 2.4
Name: tket2-exts
Version: 0.10.0
Summary: [Renamed] HUGR extension definitions for the tket2 compiler.
Project-URL: homepage, https://github.com/CQCL/tket2/tree/main/tket-exts
Project-URL: repository, https://github.com/CQCL/tket2/tree/main/tket-exts
Author-email: TKET development team <tket-support@quantinuum.com>
Maintainer-email: TKET development team <tket-support@quantinuum.com>
License:                                  Apache License
License-File: LICENCE
Classifier: Environment :: Console
Classifier: Intended Audience :: Developers
Classifier: Intended Audience :: Science/Research
Classifier: License :: OSI Approved :: Apache Software License
Classifier: Operating System :: MacOS :: MacOS X
Classifier: Operating System :: Microsoft :: Windows
Classifier: Operating System :: POSIX :: Linux
Classifier: Programming Language :: Python :: 3.10
Classifier: Programming Language :: Python :: 3.11
Classifier: Programming Language :: Python :: 3.12
Classifier: Programming Language :: Python :: 3.13
Classifier: Topic :: Scientific/Engineering
Requires-Python: >=3.10
